<?xml version="1.0" encoding="UTF-8"?>
<operations xmlns="http://aggateway.org/PAIL/0.1" xmlns:xsi="http://www.w3.org/2001/XMLSchema-instance" xsi:schemaLocation="http://aggateway.org/PAIL/0.1 ../PAIL%20xml/PAIL_Ops_029.xsd">
	<irrRefData>
		<manufacturer>
			<id>
				<referenceId>1</referenceId>
				<uniqueId>
					<idText>569d7a80e6304a50a77f936b905998c4</idText>
					<idCategory>UUID</idCategory>
				</uniqueId>
			</id>
			<description>ABC Pivot Company</description>
			<contextItem>
				<code>ExampleCode</code>
			</contextItem>
		</manufacturer>
		<systemModel>
			<id>
				<referenceId>2</referenceId>
				<uniqueId>
					<idText>4e44fd99009c4849b0c62f4e77b39350</idText>
					<idCategory>UUID</idCategory>
				</uniqueId>
			</id>
			<manufacturerRef>1</manufacturerRef>
			<description>ABC Pivot Company Model 1</description>
			<sysCategory>PIVOT</sysCategory>
		</systemModel>
		<product>
			<id>
				<referenceId>3</referenceId>
				<uniqueId>
					<idText>9b4341c0aeb04eb1812246d42db068f7</idText>
					<idCategory>UUID</idCategory>
				</uniqueId>
			</id>
			<description>An example fertilizer</description>
			<type>CROP_NUTRITION</type>
			<form>SOLID</form>
			<status>ACTIVE</status>
		</product>
	</irrRefData>
	<irrSetupData>
		<grower>
			<id>
				<referenceId>4</referenceId>
				<uniqueId>
					<idText>3f340c053dbe4b738bfe505661034797</idText>
					<idCategory>UUID</idCategory>
				</uniqueId>
			</id>
			<description>USDA- BUSHLAND, TX.</description>
		</grower>
		<farm>
			<id>
				<referenceId>5</referenceId>
				<uniqueId>
					<idText>85b082ffabf040fbaa22c1dc037a4790</idText>
					<idCategory>UUID</idCategory>
				</uniqueId>
			</id>
			<description>USDA CPRL Texas A M AgriLife Research</description>
		</farm>
		<field>
			<id>
				<referenceId>6</referenceId>
				<uniqueId>
					<idText>327c14e96a2246e8afde79ea1b71141f</idText>
					<idCategory>UUID</idCategory>
				</uniqueId>
			</id>
			<description>AgriLife Pivot with zone control VRI</description>
			<timeScope>
				<contextCategory>INSTALLATION</contextCategory>
				<stamp1>2016-01-11T00:00:00Z</stamp1>
				<description>setup data from the last time we purchased a sprinkler package</description>
			</timeScope>
			<area>
				<value>35</value>
				<unitOfMeasure>ACR</unitOfMeasure>
			</area>
			<activeBoundaryRef>7</activeBoundaryRef>
		</field>
		<fieldBoundary>
			<id>
				<referenceId>7</referenceId>
			</id>
			<description>approximate field boundary deduced from Google Earth</description>
			<fieldRef>6</fieldRef>
			<spatialData>
				<shape>POLYGON((-102.08870686006059714 35.16221494869642328,-102.08868461962100582 35.16241503868509,-102.08870873475210317 35.16267755518924076,-102.08874050191160165 35.16292158775001297,-102.08883374447749759 35.16312778854115351,-102.08896585078649366 35.16338417523798654,-102.08907473051630177 35.16358449055753965,-102.08924571573589901 35.16383491305185061,-102.08939325798090181 35.16399757561934791,-102.08968819231920122 35.16424124002759299,-102.08994451238790191 35.16443498045150307,-102.09024718505570206 35.16459058308662833,-102.09053454093489677 35.16473378577809683,-102.09089156917059427 35.16485751729113929,-102.09124807593450157 35.16491160238491887,-102.09175173385339974 35.16496448474087089,-102.09211520286839914 35.16494244986999718,-102.09254836918209719 35.16492617737289095,-102.09288002048720045 35.16485370375159647,-102.09320307484159684 35.16473699041682721,-102.09352614554110517 35.16463300686866233,-102.09380957719480421 35.16448513202915649,-102.09406948229529632 35.16433125008199312,-102.09435121211780029 35.16412049843238918,-102.09451763034479654 35.16394877667679708,-102.09472846748249708 35.16369496633100056,-102.09492265331660121 35.16339763436147337,-102.09506248655209504 35.16309496344290153,-102.09515592829180264 35.16279318336169268,-102.09519610347270202 35.16252362881712656,-102.09519725706699944 35.16222981646617285,-102.08870686006059714 35.16221494869642328))</shape>
			</spatialData>
		</fieldBoundary>
		<irrSystem>
			<id>
				<referenceId>8</referenceId>
				<uniqueId>
					<idText>ccd76564c09d473f91620c486ed0d54a</idText>
					<idCategory>UUID</idCategory>
				</uniqueId>
			</id>
			<description>half circle pivot on the south section of the Bushland farm</description>
			<systemModelRef>2</systemModelRef>
			<systemCategory>PIVOT</systemCategory>
		</irrSystem>
		<irrSetup>
			<id>
				<referenceId>9</referenceId>
				<uniqueId>
					<idText>27f785391df54d35b728ed8363468d76</idText>
					<idCategory>UUID</idCategory>
				</uniqueId>
			</id>
			<sectionSetup>
				<sectionId>
					<referenceId>1</referenceId>
				</sectionId>
				<sectionCategory>SPAN</sectionCategory>
				<innerDistance>41.4</innerDistance>
				<outerDistance>160.0</outerDistance>
			</sectionSetup>
			<sectionSetup>
				<sectionId>
					<referenceId>2</referenceId>
				</sectionId>
				<sectionCategory>SPAN</sectionCategory>
				<innerDistance>160.0</innerDistance>
				<outerDistance>320.9</outerDistance>
			</sectionSetup>
			<sectionSetup>
				<sectionId>
					<referenceId>3</referenceId>
				</sectionId>
				<sectionCategory>SPAN</sectionCategory>
				<innerDistance>320.9</innerDistance>
				<outerDistance>480.9</outerDistance>
			</sectionSetup>
			<sectionSetup>
				<sectionId>
					<referenceId>4</referenceId>
				</sectionId>
				<sectionCategory>SPAN</sectionCategory>
				<innerDistance>480.9</innerDistance>
				<outerDistance>640.9</outerDistance>
			</sectionSetup>
			<sectionSetup>
				<sectionId>
					<referenceId>5</referenceId>
				</sectionId>
				<sectionCategory>SPAN</sectionCategory>
				<innerDistance>640.9</innerDistance>
				<outerDistance>801.0</outerDistance>
			</sectionSetup>
			<sectionSetup>
				<sectionId>
					<referenceId>6</referenceId>
				</sectionId>
				<sectionCategory>SPAN</sectionCategory>
				<innerDistance>801.0</innerDistance>
				<outerDistance>960.8</outerDistance>
			</sectionSetup>
			<sectionSetup>
				<sectionId>
					<referenceId>7</referenceId>
				</sectionId>
				<sectionCategory>SPAN</sectionCategory>
				<innerDistance>960.8</innerDistance>
				<outerDistance>978.9</outerDistance>
			</sectionSetup>
			<locationDataPedigree>MANUAL_INPUT</locationDataPedigree>
			<timeDataPedigree>UNKNOWN</timeDataPedigree>
			<timeScope>
				<contextCategory>INSTALLATION</contextCategory>
				<stamp1>2016-01-11T00:00:00Z</stamp1>
			</timeScope>
			<systemLength>978.9</systemLength>
			<lengthUoM>FOT</lengthUoM>
			<areaTotalUoM>ACR</areaTotalUoM>
			<nominalPressure>17</nominalPressure>
			<nominalEfficiency>90</nominalEfficiency>
			<pressureUoM>PS</pressureUoM>
			<pressureLocation>AT_BASE_OF_SYSTEM</pressureLocation>
			<nominalFlow>300</nominalFlow>
			<flowUoM>G2</flowUoM>
			<depthUoM>INH</depthUoM>
			<nominalFullCircleTime>PT6H6M</nominalFullCircleTime>
		</irrSetup>
	</irrSetupData>
	<irrDocs>
		<irrWorkOrder>
			<id>
				<referenceId>10</referenceId>
				<uniqueId>
					<idText>35d4bc451125443eb6928334956d26c4</idText>
					<idCategory>UUID</idCategory>
				</uniqueId>
			</id>
			<description>Example work order</description>
			<setupRef>9</setupRef>
			<irrColl>
				<timeScope>
					<contextCategory>PROPOSED_START</contextCategory>
					<stamp1>2017-06-04T00:08:00-06:00</stamp1>
				</timeScope>
				<irrItem>
					<sectionFlow>
						<sectionRef>1</sectionRef>
						<depth>1</depth>
					</sectionFlow>
					<sectionFlow>
						<sectionRef>2</sectionRef>
						<depth>1</depth>
					</sectionFlow>
					<sectionFlow>
						<sectionRef>3</sectionRef>
						<depth>1</depth>
					</sectionFlow>
					<sectionFlow>
						<sectionRef>4</sectionRef>
						<depth>1</depth>
					</sectionFlow>
					<sectionFlow>
						<sectionRef>5</sectionRef>
						<depth>1</depth>
					</sectionFlow>
					<sectionFlow>
						<sectionRef>6</sectionRef>
						<depth>1</depth>
					</sectionFlow>
					<sectionFlow>
						<sectionRef>7</sectionRef>
						<depth>1</depth>
					</sectionFlow>
				</irrItem>
			</irrColl>
		</irrWorkOrder>
		<irrWorkRecord>
			<id>
				<referenceId>11</referenceId>
				<uniqueId>
					<idText>0468ecfd97974a989b5a4e5bfbf79de5</idText>
					<idCategory>UUID</idCategory>
				</uniqueId>
			</id>
			<description>example work record, corresponding to the WorkOrder in this document.  The same depth was applied but the irrigation starts two hours later than the WorkOrder specified.  Note that a different Context is used in the TimeScope for the start time.</description>
			<setupRef>9</setupRef>
			<irrColl>
				<timeScope>
					<contextCategory>ACTUAL_START</contextCategory>
					<stamp1>2017-06-04T00:10:00-06:00</stamp1>
				</timeScope>
				<irrItem>
					<sectionFlow>
						<sectionRef>1</sectionRef>
						<depth>1</depth>
					</sectionFlow>
					<sectionFlow>
						<sectionRef>2</sectionRef>
						<depth>1</depth>
					</sectionFlow>
					<sectionFlow>
						<sectionRef>3</sectionRef>
						<depth>1</depth>
					</sectionFlow>
					<sectionFlow>
						<sectionRef>4</sectionRef>
						<depth>1</depth>
					</sectionFlow>
					<sectionFlow>
						<sectionRef>5</sectionRef>
						<depth>1</depth>
					</sectionFlow>
					<sectionFlow>
						<sectionRef>6</sectionRef>
						<depth>1</depth>
					</sectionFlow>
					<sectionFlow>
						<sectionRef>7</sectionRef>
						<depth>1</depth>
					</sectionFlow>
				</irrItem>
			</irrColl>
			<originatingWorkOrderRef>10</originatingWorkOrderRef>
		</irrWorkRecord>
	</irrDocs>
	<unitOfMeasureAuthority>UNREC20</unitOfMeasureAuthority>
</operations>
